{
  "config": {
    "configFile": "C:\\Users\\vanei\\OneDrive\\Desktop\\Playwright\\playwright.config.js",
    "rootDir": "C:/Users/vanei/OneDrive/Desktop/Playwright/tests",
    "forbidOnly": false,
    "fullyParallel": true,
    "globalSetup": null,
    "globalTeardown": null,
    "globalTimeout": 0,
    "grep": {},
    "grepInvert": null,
    "maxFailures": 0,
    "metadata": {
      "actualWorkers": 4
    },
    "preserveOutput": "always",
    "projects": [
      {
        "outputDir": "C:/Users/vanei/OneDrive/Desktop/Playwright/test-results",
        "repeatEach": 1,
        "retries": 2,
        "metadata": {
          "actualWorkers": 4
        },
        "id": "setup",
        "name": "setup",
        "testDir": "C:/Users/vanei/OneDrive/Desktop/Playwright/tests",
        "testIgnore": [],
        "testMatch": [
          "/.*\\.setup\\.ts/"
        ],
        "timeout": 90000
      },
      {
        "outputDir": "C:/Users/vanei/OneDrive/Desktop/Playwright/test-results",
        "repeatEach": 1,
        "retries": 2,
        "metadata": {
          "actualWorkers": 4
        },
        "id": "chromium",
        "name": "chromium",
        "testDir": "C:/Users/vanei/OneDrive/Desktop/Playwright/tests",
        "testIgnore": [],
        "testMatch": [
          "**/*.@(spec|test).?(c|m)[jt]s?(x)"
        ],
        "timeout": 90000
      }
    ],
    "quiet": false,
    "reporter": [
      [
        "json",
        {
          "outputFile": "results.json"
        }
      ],
      [
        "html",
        {
          "open": "never"
        }
      ]
    ],
    "reportSlowTests": {
      "max": 5,
      "threshold": 300000
    },
    "runAgents": "none",
    "shard": null,
    "tags": [],
    "updateSnapshots": "missing",
    "updateSourceMethod": "patch",
    "version": "1.58.2",
    "workers": 7,
    "webServer": null
  },
  "suites": [
    {
      "title": "auth.setup.ts",
      "file": "auth.setup.ts",
      "column": 0,
      "line": 0,
      "specs": [
        {
          "title": "authenticate",
          "ok": true,
          "tags": [],
          "tests": [
            {
              "timeout": 90000,
              "annotations": [],
              "expectedStatus": "passed",
              "projectId": "setup",
              "projectName": "setup",
              "results": [
                {
                  "workerIndex": 0,
                  "parallelIndex": 0,
                  "status": "passed",
                  "duration": 172,
                  "errors": [],
                  "stdout": [],
                  "stderr": [],
                  "retry": 0,
                  "startTime": "2026-06-02T23:12:20.667Z",
                  "annotations": [],
                  "attachments": []
                }
              ],
              "status": "expected"
            }
          ],
          "id": "17e3fe6f4d9d8bd79c6b-60f085b113a677673906",
          "file": "auth.setup.ts",
          "line": 10,
          "column": 6
        }
      ]
    },
    {
      "title": "wolf-tests\\differentCurrencyWolf.spec.js",
      "file": "wolf-tests/differentCurrencyWolf.spec.js",
      "column": 0,
      "line": 0,
      "specs": [
        {
          "title": "Different currency payment - Wolf and CC update",
          "ok": true,
          "tags": [],
          "tests": [
            {
              "timeout": 270000,
              "annotations": [
                {
                  "type": "slow",
                  "location": {
                    "file": "C:\\Users\\vanei\\OneDrive\\Desktop\\Playwright\\tests\\wolf-tests\\differentCurrencyWolf.spec.js",
                    "line": 11,
                    "column": 8
                  }
                }
              ],
              "expectedStatus": "passed",
              "projectId": "chromium",
              "projectName": "chromium",
              "results": [
                {
                  "workerIndex": 1,
                  "parallelIndex": 0,
                  "status": "failed",
                  "duration": 91230,
                  "error": {
                    "message": "Error: \u001b[2mexpect(\u001b[22m\u001b[31mlocator\u001b[39m\u001b[2m).\u001b[22mtoBeEnabled\u001b[2m(\u001b[22m\u001b[2m)\u001b[22m failed\n\nLocator:  locator('id=btnSubmitApplication')\nExpected: enabled\nReceived: disabled\nTimeout:  5000ms\n\nCall log:\n\u001b[2m  - Expect \"toBeEnabled\" with timeout 5000ms\u001b[22m\n\u001b[2m  - waiting for locator('id=btnSubmitApplication')\u001b[22m\n\u001b[2m    9 × locator resolved to <button disabled type=\"submit\" class=\"yx yy yj yo\" aria-disabled=\"true\" id=\"btnSubmitApplication\">…</button>\u001b[22m\n\u001b[2m      - unexpected value \"disabled\"\u001b[22m\n",
                    "stack": "Error: \u001b[2mexpect(\u001b[22m\u001b[31mlocator\u001b[39m\u001b[2m).\u001b[22mtoBeEnabled\u001b[2m(\u001b[22m\u001b[2m)\u001b[22m failed\n\nLocator:  locator('id=btnSubmitApplication')\nExpected: enabled\nReceived: disabled\nTimeout:  5000ms\n\nCall log:\n\u001b[2m  - Expect \"toBeEnabled\" with timeout 5000ms\u001b[22m\n\u001b[2m  - waiting for locator('id=btnSubmitApplication')\u001b[22m\n\u001b[2m    9 × locator resolved to <button disabled type=\"submit\" class=\"yx yy yj yo\" aria-disabled=\"true\" id=\"btnSubmitApplication\">…</button>\u001b[22m\n\u001b[2m      - unexpected value \"disabled\"\u001b[22m\n\n    at C:\\Users\\vanei\\OneDrive\\Desktop\\Playwright\\tests\\wolf-tests\\differentCurrencyWolf.spec.js:97:37",
                    "location": {
                      "file": "C:\\Users\\vanei\\OneDrive\\Desktop\\Playwright\\tests\\wolf-tests\\differentCurrencyWolf.spec.js",
                      "column": 37,
                      "line": 97
                    },
                    "snippet": "\u001b[0m \u001b[90m  95 |\u001b[39m   \u001b[36mawait\u001b[39m selectors\u001b[33m.\u001b[39mdropdownSelector(page\u001b[33m,\u001b[39m \u001b[32m\"applicant.0.birth_country\"\u001b[39m\u001b[33m,\u001b[39m \u001b[32m\"dropdown-applicant.0.birth_country\"\u001b[39m\u001b[33m,\u001b[39m \u001b[32m\"mexico\"\u001b[39m\u001b[33m,\u001b[39m \u001b[32m\"MX\"\u001b[39m)\n \u001b[90m  96 |\u001b[39m   \u001b[36mconst\u001b[39m submit_post_payment \u001b[33m=\u001b[39m page\u001b[33m.\u001b[39mlocator(\u001b[32m'id=btnSubmitApplication'\u001b[39m)\n\u001b[31m\u001b[1m>\u001b[22m\u001b[39m\u001b[90m  97 |\u001b[39m   \u001b[36mawait\u001b[39m expect(submit_post_payment)\u001b[33m.\u001b[39mtoBeEnabled()\n \u001b[90m     |\u001b[39m                                     \u001b[31m\u001b[1m^\u001b[22m\u001b[39m\n \u001b[90m  98 |\u001b[39m   \u001b[36mawait\u001b[39m submit_post_payment\u001b[33m.\u001b[39mclick()\n \u001b[90m  99 |\u001b[39m   \u001b[36mawait\u001b[39m page\u001b[33m.\u001b[39mwaitForNavigation({waitUntil\u001b[33m:\u001b[39m \u001b[32m'load'\u001b[39m})\n \u001b[90m 100 |\u001b[39m\u001b[0m"
                  },
                  "errors": [
                    {
                      "location": {
                        "file": "C:\\Users\\vanei\\OneDrive\\Desktop\\Playwright\\tests\\wolf-tests\\differentCurrencyWolf.spec.js",
                        "column": 37,
                        "line": 97
                      },
                      "message": "Error: \u001b[2mexpect(\u001b[22m\u001b[31mlocator\u001b[39m\u001b[2m).\u001b[22mtoBeEnabled\u001b[2m(\u001b[22m\u001b[2m)\u001b[22m failed\n\nLocator:  locator('id=btnSubmitApplication')\nExpected: enabled\nReceived: disabled\nTimeout:  5000ms\n\nCall log:\n\u001b[2m  - Expect \"toBeEnabled\" with timeout 5000ms\u001b[22m\n\u001b[2m  - waiting for locator('id=btnSubmitApplication')\u001b[22m\n\u001b[2m    9 × locator resolved to <button disabled type=\"submit\" class=\"yx yy yj yo\" aria-disabled=\"true\" id=\"btnSubmitApplication\">…</button>\u001b[22m\n\u001b[2m      - unexpected value \"disabled\"\u001b[22m\n\n\n\u001b[0m \u001b[90m  95 |\u001b[39m   \u001b[36mawait\u001b[39m selectors\u001b[33m.\u001b[39mdropdownSelector(page\u001b[33m,\u001b[39m \u001b[32m\"applicant.0.birth_country\"\u001b[39m\u001b[33m,\u001b[39m \u001b[32m\"dropdown-applicant.0.birth_country\"\u001b[39m\u001b[33m,\u001b[39m \u001b[32m\"mexico\"\u001b[39m\u001b[33m,\u001b[39m \u001b[32m\"MX\"\u001b[39m)\n \u001b[90m  96 |\u001b[39m   \u001b[36mconst\u001b[39m submit_post_payment \u001b[33m=\u001b[39m page\u001b[33m.\u001b[39mlocator(\u001b[32m'id=btnSubmitApplication'\u001b[39m)\n\u001b[31m\u001b[1m>\u001b[22m\u001b[39m\u001b[90m  97 |\u001b[39m   \u001b[36mawait\u001b[39m expect(submit_post_payment)\u001b[33m.\u001b[39mtoBeEnabled()\n \u001b[90m     |\u001b[39m                                     \u001b[31m\u001b[1m^\u001b[22m\u001b[39m\n \u001b[90m  98 |\u001b[39m   \u001b[36mawait\u001b[39m submit_post_payment\u001b[33m.\u001b[39mclick()\n \u001b[90m  99 |\u001b[39m   \u001b[36mawait\u001b[39m page\u001b[33m.\u001b[39mwaitForNavigation({waitUntil\u001b[33m:\u001b[39m \u001b[32m'load'\u001b[39m})\n \u001b[90m 100 |\u001b[39m\u001b[0m\n\u001b[2m    at C:\\Users\\vanei\\OneDrive\\Desktop\\Playwright\\tests\\wolf-tests\\differentCurrencyWolf.spec.js:97:37\u001b[22m"
                    }
                  ],
                  "stdout": [],
                  "stderr": [],
                  "retry": 0,
                  "startTime": "2026-06-02T23:12:24.984Z",
                  "annotations": [
                    {
                      "type": "slow",
                      "location": {
                        "file": "C:\\Users\\vanei\\OneDrive\\Desktop\\Playwright\\tests\\wolf-tests\\differentCurrencyWolf.spec.js",
                        "line": 11,
                        "column": 8
                      }
                    }
                  ],
                  "attachments": [
                    {
                      "name": "video",
                      "contentType": "video/webm",
                      "path": "C:\\Users\\vanei\\OneDrive\\Desktop\\Playwright\\test-results\\wolf-tests-differentCurren-e9e29-ayment---Wolf-and-CC-update-chromium\\video.webm"
                    },
                    {
                      "name": "error-context",
                      "contentType": "text/markdown",
                      "path": "C:\\Users\\vanei\\OneDrive\\Desktop\\Playwright\\test-results\\wolf-tests-differentCurren-e9e29-ayment---Wolf-and-CC-update-chromium\\error-context.md"
                    }
                  ],
                  "errorLocation": {
                    "file": "C:\\Users\\vanei\\OneDrive\\Desktop\\Playwright\\tests\\wolf-tests\\differentCurrencyWolf.spec.js",
                    "column": 37,
                    "line": 97
                  }
                },
                {
                  "workerIndex": 5,
                  "parallelIndex": 0,
                  "status": "passed",
                  "duration": 123223,
                  "errors": [],
                  "stdout": [],
                  "stderr": [],
                  "retry": 1,
                  "startTime": "2026-06-02T23:13:59.744Z",
                  "annotations": [
                    {
                      "type": "slow",
                      "location": {
                        "file": "C:\\Users\\vanei\\OneDrive\\Desktop\\Playwright\\tests\\wolf-tests\\differentCurrencyWolf.spec.js",
                        "line": 11,
                        "column": 8
                      }
                    }
                  ],
                  "attachments": [
                    {
                      "name": "video",
                      "contentType": "video/webm",
                      "path": "C:\\Users\\vanei\\OneDrive\\Desktop\\Playwright\\test-results\\wolf-tests-differentCurren-e9e29-ayment---Wolf-and-CC-update-chromium-retry1\\video.webm"
                    },
                    {
                      "name": "trace",
                      "contentType": "application/zip",
                      "path": "C:\\Users\\vanei\\OneDrive\\Desktop\\Playwright\\test-results\\wolf-tests-differentCurren-e9e29-ayment---Wolf-and-CC-update-chromium-retry1\\trace.zip"
                    }
                  ]
                }
              ],
              "status": "flaky"
            }
          ],
          "id": "ff7a6c0c6ae64298920b-18f9b5ec52aebdd50400",
          "file": "wolf-tests/differentCurrencyWolf.spec.js",
          "line": 10,
          "column": 1
        }
      ]
    },
    {
      "title": "wolf-tests\\fileUploadWolf.spec.js",
      "file": "wolf-tests/fileUploadWolf.spec.js",
      "column": 0,
      "line": 0,
      "specs": [
        {
          "title": "File upload - Wolf",
          "ok": true,
          "tags": [],
          "tests": [
            {
              "timeout": 270000,
              "annotations": [
                {
                  "type": "slow",
                  "location": {
                    "file": "C:\\Users\\vanei\\OneDrive\\Desktop\\Playwright\\tests\\wolf-tests\\fileUploadWolf.spec.js",
                    "line": 11,
                    "column": 8
                  }
                }
              ],
              "expectedStatus": "passed",
              "projectId": "chromium",
              "projectName": "chromium",
              "results": [
                {
                  "workerIndex": 2,
                  "parallelIndex": 1,
                  "status": "passed",
                  "duration": 107737,
                  "errors": [],
                  "stdout": [],
                  "stderr": [],
                  "retry": 0,
                  "startTime": "2026-06-02T23:12:25.121Z",
                  "annotations": [
                    {
                      "type": "slow",
                      "location": {
                        "file": "C:\\Users\\vanei\\OneDrive\\Desktop\\Playwright\\tests\\wolf-tests\\fileUploadWolf.spec.js",
                        "line": 11,
                        "column": 8
                      }
                    }
                  ],
                  "attachments": [
                    {
                      "name": "video",
                      "contentType": "video/webm",
                      "path": "C:\\Users\\vanei\\OneDrive\\Desktop\\Playwright\\test-results\\wolf-tests-fileUploadWolf-File-upload---Wolf-chromium\\video.webm"
                    }
                  ]
                }
              ],
              "status": "expected"
            }
          ],
          "id": "77ec0eab2c742886dd35-a0db35bbad8760ffbf3b",
          "file": "wolf-tests/fileUploadWolf.spec.js",
          "line": 10,
          "column": 1
        }
      ]
    },
    {
      "title": "wolf-tests\\individualSubscription.spec.js",
      "file": "wolf-tests/individualSubscription.spec.js",
      "column": 0,
      "line": 0,
      "specs": [
        {
          "title": "Individual subscription purchase - Wolf",
          "ok": true,
          "tags": [],
          "tests": [
            {
              "timeout": 270000,
              "annotations": [
                {
                  "type": "slow",
                  "location": {
                    "file": "C:\\Users\\vanei\\OneDrive\\Desktop\\Playwright\\tests\\wolf-tests\\individualSubscription.spec.js",
                    "line": 11,
                    "column": 8
                  }
                }
              ],
              "expectedStatus": "passed",
              "projectId": "chromium",
              "projectName": "chromium",
              "results": [
                {
                  "workerIndex": 3,
                  "parallelIndex": 2,
                  "status": "passed",
                  "duration": 181248,
                  "errors": [],
                  "stdout": [],
                  "stderr": [],
                  "retry": 0,
                  "startTime": "2026-06-02T23:12:24.966Z",
                  "annotations": [
                    {
                      "type": "slow",
                      "location": {
                        "file": "C:\\Users\\vanei\\OneDrive\\Desktop\\Playwright\\tests\\wolf-tests\\individualSubscription.spec.js",
                        "line": 11,
                        "column": 8
                      }
                    }
                  ],
                  "attachments": [
                    {
                      "name": "video",
                      "contentType": "video/webm",
                      "path": "C:\\Users\\vanei\\OneDrive\\Desktop\\Playwright\\test-results\\wolf-tests-individualSubsc-08406-ubscription-purchase---Wolf-chromium\\video.webm"
                    }
                  ]
                }
              ],
              "status": "expected"
            }
          ],
          "id": "f430faf524dea75d05c8-6f3fa6c787ecccdd63c0",
          "file": "wolf-tests/individualSubscription.spec.js",
          "line": 10,
          "column": 1
        }
      ]
    },
    {
      "title": "wolf-tests\\passwordWolf.spec.js",
      "file": "wolf-tests/passwordWolf.spec.js",
      "column": 0,
      "line": 0,
      "specs": [
        {
          "title": "Password Creation and login - Wolf",
          "ok": true,
          "tags": [],
          "tests": [
            {
              "timeout": 270000,
              "annotations": [
                {
                  "type": "slow",
                  "location": {
                    "file": "C:\\Users\\vanei\\OneDrive\\Desktop\\Playwright\\tests\\wolf-tests\\passwordWolf.spec.js",
                    "line": 10,
                    "column": 8
                  }
                }
              ],
              "expectedStatus": "passed",
              "projectId": "chromium",
              "projectName": "chromium",
              "results": [
                {
                  "workerIndex": 4,
                  "parallelIndex": 3,
                  "status": "passed",
                  "duration": 65576,
                  "errors": [],
                  "stdout": [],
                  "stderr": [],
                  "retry": 0,
                  "startTime": "2026-06-02T23:12:25.129Z",
                  "annotations": [
                    {
                      "type": "slow",
                      "location": {
                        "file": "C:\\Users\\vanei\\OneDrive\\Desktop\\Playwright\\tests\\wolf-tests\\passwordWolf.spec.js",
                        "line": 10,
                        "column": 8
                      }
                    }
                  ],
                  "attachments": [
                    {
                      "name": "video",
                      "contentType": "video/webm",
                      "path": "C:\\Users\\vanei\\OneDrive\\Desktop\\Playwright\\test-results\\wolf-tests-passwordWolf-Password-Creation-and-login---Wolf-chromium\\video.webm"
                    }
                  ]
                }
              ],
              "status": "expected"
            }
          ],
          "id": "246ec87d5e74e468a0aa-9d42dabe8e38d7884464",
          "file": "wolf-tests/passwordWolf.spec.js",
          "line": 9,
          "column": 1
        }
      ]
    }
  ],
  "errors": [],
  "stats": {
    "startTime": "2026-06-02T23:12:19.236Z",
    "duration": 232957.529,
    "expected": 4,
    "skipped": 0,
    "unexpected": 0,
    "flaky": 1
  }
}